GINSA/GINSA_cli.py
GINSA/GINSA_gui.py
GINSA/__init__.py
ginsa-1.0.0.dist-info/entry_points.txt
ginsa-1.0.0.dist-info/WHEEL
ginsa-1.0.0.dist-info/METADATA
ginsa-1.0.0.dist-info/RECORD
