Metadata-Version: 2.1
Name: GINSA
Version: 1.0.0
Summary: GINSA
Author-email: Eric Odle <eo@hokudai.me.uk>
Requires-Python: >=3.10
Classifier: License :: OSI Approved :: MIT License
Requires-Dist: anyio==4.2.0
Requires-Dist: biopython==1.83
Requires-Dist: certifi==2024.2.2
Requires-Dist: charset-normalizer==3.3.2
Requires-Dist: contourpy==1.2.0
Requires-Dist: cycler==0.12.1
Requires-Dist: docutils==0.20.1
Requires-Dist: fonttools==4.47.2
Requires-Dist: h11==0.14.0
Requires-Dist: httpcore==1.0.2
Requires-Dist: httpx==0.26.0
Requires-Dist: idna==3.6
Requires-Dist: importlib-metadata==7.0.1
Requires-Dist: iniconfig==2.0.0
Requires-Dist: jaraco.classes==3.3.0
Requires-Dist: keyring==24.3.0
Requires-Dist: kiwisolver==1.4.5
Requires-Dist: markdown-it-py==3.0.0
Requires-Dist: matplotlib==3.8.2
Requires-Dist: mdurl==0.1.2
Requires-Dist: more-itertools==10.2.0
Requires-Dist: nh3==0.2.15
Requires-Dist: numpy==1.26.3
Requires-Dist: packaging==23.2
Requires-Dist: pandas==2.2.0
Requires-Dist: pillow==10.2.0
Requires-Dist: pkginfo==1.9.6
Requires-Dist: pluggy==1.4.0
Requires-Dist: psutil==5.9.8
Requires-Dist: Pygments==2.17.2
Requires-Dist: pyparsing==3.1.1
Requires-Dist: pytest==8.0.0
Requires-Dist: python-dateutil==2.8.2
Requires-Dist: pytz==2024.1
Requires-Dist: readme-renderer==42.0
Requires-Dist: requests==2.31.0
Requires-Dist: requests-toolbelt==1.0.0
Requires-Dist: rfc3986==2.0.0
Requires-Dist: rich==13.7.0
Requires-Dist: setuptools==69.0.3
Requires-Dist: six==1.16.0
Requires-Dist: sniffio==1.3.0
Requires-Dist: tk==0.1.0
Requires-Dist: twine==4.0.2
Requires-Dist: tzdata==2023.4
Requires-Dist: urllib3==2.2.0
Requires-Dist: wget==3.2
Requires-Dist: wheel==0.42.0
Requires-Dist: zipp==3.17.0
